{
    "name": "Loops & Lantanas – LL11",
    "features": {},
    "customizations": {
      "vscode": {
        "extensions": [
          "ritwickdey.LiveServer",       // Adds the Live Server extension
          "ms-vsliveshare.vsliveshare"   // Adds the Live Share extension
        ]
      }
    },
    "forwardPorts": [5500],
    "portsAttributes": {
      "5500": {
        "label": "Live Server",
        "onAutoForward": "openBrowser"
      }
    },
    "postCreateCommand": "echo '🌼 Welcome to Loops & Lantanas – LL11 Codespace! Time to build your feature for the Lantana Alliance 🌿'"
  }
  